{"nodes": [{"id": "d_workspace_vim_with_mouse_src_huntandpeck_app_xaml_cs", "label": "App.xaml.cs", "file_type": "code", "source_file": "src/HuntAndPeck/App.xaml.cs", "source_location": "L1"}, {"id": "huntandpeck_app_xaml_huntandpeck", "label": "HuntAndPeck", "file_type": "code", "source_file": "src/HuntAndPeck/App.xaml.cs", "source_location": "L10"}, {"id": "huntandpeck_app_xaml_app", "label": "App", "file_type": "code", "source_file": "src/HuntAndPeck/App.xaml.cs", "source_location": "L15"}, {"id": "application", "label": "Application", "file_type": "code", "source_file": "", "source_location": ""}, {"id": "singlelaunchmutex", "label": "SingleLaunchMutex", "file_type": "code", "source_file": "src/HuntAndPeck/App.xaml.cs", "source_location": "L17"}, {"id": "uiautomationhintproviderservice", "label": "UiAutomationHintProviderService", "file_type": "code", "source_file": "src/HuntAndPeck/App.xaml.cs", "source_location": "L18"}, {"id": "hintlabelservice", "label": "HintLabelService", "file_type": "code", "source_file": "src/HuntAndPeck/App.xaml.cs", "source_location": "L20"}, {"id": "keylistenerservice", "label": "KeyListenerService", "file_type": "code", "source_file": "src/HuntAndPeck/App.xaml.cs", "source_location": "L21"}, {"id": "huntandpeck_app_xaml_app_showoverlay", "label": ".ShowOverlay()", "file_type": "code", "source_file": "src/HuntAndPeck/App.xaml.cs", "source_location": "L35"}, {"id": "overlayviewmodel", "label": "OverlayViewModel", "file_type": "code", "source_file": "src/HuntAndPeck/App.xaml.cs", "source_location": "L35"}, {"id": "huntandpeck_app_xaml_app_showdebugoverlay", "label": ".ShowDebugOverlay()", "file_type": "code", "source_file": "src/HuntAndPeck/App.xaml.cs", "source_location": "L46"}, {"id": "debugoverlayviewmodel", "label": "DebugOverlayViewModel", "file_type": "code", "source_file": "src/HuntAndPeck/App.xaml.cs", "source_location": "L46"}, {"id": "huntandpeck_app_xaml_app_showoptions", "label": ".ShowOptions()", "file_type": "code", "source_file": "src/HuntAndPeck/App.xaml.cs", "source_location": "L55"}, {"id": "optionsviewmodel", "label": "OptionsViewModel", "file_type": "code", "source_file": "src/HuntAndPeck/App.xaml.cs", "source_location": "L55"}, {"id": "huntandpeck_app_xaml_app_onstartup", "label": ".OnStartup()", "file_type": "code", "source_file": "src/HuntAndPeck/App.xaml.cs", "source_location": "L64"}, {"id": "startupeventargs", "label": "StartupEventArgs", "file_type": "code", "source_file": "src/HuntAndPeck/App.xaml.cs", "source_location": "L64"}], "edges": [{"source": "d_workspace_vim_with_mouse_src_huntandpeck_app_xaml_cs", "target": "system", "relation": "imports", "context": "import", "confidence": "EXTRACTED", "source_file": "src/HuntAndPeck/App.xaml.cs", "source_location": "L1", "weight": 1.0}, {"source": "d_workspace_vim_with_mouse_src_huntandpeck_app_xaml_cs", "target": "windows", "relation": "imports", "context": "import", "confidence": "EXTRACTED", "source_file": "src/HuntAndPeck/App.xaml.cs", "source_location": "L2", "weight": 1.0}, {"source": "d_workspace_vim_with_mouse_src_huntandpeck_app_xaml_cs", "target": "viewmodels", "relation": "imports", "context": "import", "confidence": "EXTRACTED", "source_file": "src/HuntAndPeck/App.xaml.cs", "source_location": "L3", "weight": 1.0}, {"source": "d_workspace_vim_with_mouse_src_huntandpeck_app_xaml_cs", "target": "linq", "relation": "imports", "context": "import", "confidence": "EXTRACTED", "source_file": "src/HuntAndPeck/App.xaml.cs", "source_location": "L4", "weight": 1.0}, {"source": "d_workspace_vim_with_mouse_src_huntandpeck_app_xaml_cs", "target": "diagnostics", "relation": "imports", "context": "import", "confidence": "EXTRACTED", "source_file": "src/HuntAndPeck/App.xaml.cs", "source_location": "L5", "weight": 1.0}, {"source": "d_workspace_vim_with_mouse_src_huntandpeck_app_xaml_cs", "target": "services", "relation": "imports", "context": "import", "confidence": "EXTRACTED", "source_file": "src/HuntAndPeck/App.xaml.cs", "source_location": "L6", "weight": 1.0}, {"source": "d_workspace_vim_with_mouse_src_huntandpeck_app_xaml_cs", "target": "views", "relation": "imports", "context": "import", "confidence": "EXTRACTED", "source_file": "src/HuntAndPeck/App.xaml.cs", "source_location": "L7", "weight": 1.0}, {"source": "d_workspace_vim_with_mouse_src_huntandpeck_app_xaml_cs", "target": "nativemethods", "relation": "imports", "context": "import", "confidence": "EXTRACTED", "source_file": "src/HuntAndPeck/App.xaml.cs", "source_location": "L8", "weight": 1.0}, {"source": "d_workspace_vim_with_mouse_src_huntandpeck_app_xaml_cs", "target": "huntandpeck_app_xaml_huntandpeck", "relation": "contains", "confidence": "EXTRACTED", "source_file": "src/HuntAndPeck/App.xaml.cs", "source_location": "L10", "weight": 1.0}, {"source": "d_workspace_vim_with_mouse_src_huntandpeck_app_xaml_cs", "target": "huntandpeck_app_xaml_app", "relation": "contains", "confidence": "EXTRACTED", "source_file": "src/HuntAndPeck/App.xaml.cs", "source_location": "L15", "weight": 1.0}, {"source": "huntandpeck_app_xaml_app", "target": "application", "relation": "inherits", "confidence": "EXTRACTED", "source_file": "src/HuntAndPeck/App.xaml.cs", "source_location": "L15", "weight": 1.0}, {"source": "huntandpeck_app_xaml_app", "target": "singlelaunchmutex", "relation": "references", "confidence": "EXTRACTED", "source_file": "src/HuntAndPeck/App.xaml.cs", "source_location": "L17", "weight": 1.0, "context": "field"}, {"source": "huntandpeck_app_xaml_app", "target": "uiautomationhintproviderservice", "relation": "references", "confidence": "EXTRACTED", "source_file": "src/HuntAndPeck/App.xaml.cs", "source_location": "L18", "weight": 1.0, "context": "field"}, {"source": "huntandpeck_app_xaml_app", "target": "hintlabelservice", "relation": "references", "confidence": "EXTRACTED", "source_file": "src/HuntAndPeck/App.xaml.cs", "source_location": "L20", "weight": 1.0, "context": "field"}, {"source": "huntandpeck_app_xaml_app", "target": "keylistenerservice", "relation": "references", "confidence": "EXTRACTED", "source_file": "src/HuntAndPeck/App.xaml.cs", "source_location": "L21", "weight": 1.0, "context": "field"}, {"source": "huntandpeck_app_xaml_app", "target": "huntandpeck_app_xaml_app_showoverlay", "relation": "method", "confidence": "EXTRACTED", "source_file": "src/HuntAndPeck/App.xaml.cs", "source_location": "L35", "weight": 1.0}, {"source": "huntandpeck_app_xaml_app_showoverlay", "target": "overlayviewmodel", "relation": "references", "confidence": "EXTRACTED", "source_file": "src/HuntAndPeck/App.xaml.cs", "source_location": "L35", "weight": 1.0, "context": "parameter_type"}, {"source": "huntandpeck_app_xaml_app", "target": "huntandpeck_app_xaml_app_showdebugoverlay", "relation": "method", "confidence": "EXTRACTED", "source_file": "src/HuntAndPeck/App.xaml.cs", "source_location": "L46", "weight": 1.0}, {"source": "huntandpeck_app_xaml_app_showdebugoverlay", "target": "debugoverlayviewmodel", "relation": "references", "confidence": "EXTRACTED", "source_file": "src/HuntAndPeck/App.xaml.cs", "source_location": "L46", "weight": 1.0, "context": "parameter_type"}, {"source": "huntandpeck_app_xaml_app", "target": "huntandpeck_app_xaml_app_showoptions", "relation": "method", "confidence": "EXTRACTED", "source_file": "src/HuntAndPeck/App.xaml.cs", "source_location": "L55", "weight": 1.0}, {"source": "huntandpeck_app_xaml_app_showoptions", "target": "optionsviewmodel", "relation": "references", "confidence": "EXTRACTED", "source_file": "src/HuntAndPeck/App.xaml.cs", "source_location": "L55", "weight": 1.0, "context": "parameter_type"}, {"source": "huntandpeck_app_xaml_app", "target": "huntandpeck_app_xaml_app_onstartup", "relation": "method", "confidence": "EXTRACTED", "source_file": "src/HuntAndPeck/App.xaml.cs", "source_location": "L64", "weight": 1.0}, {"source": "huntandpeck_app_xaml_app_onstartup", "target": "startupeventargs", "relation": "references", "confidence": "EXTRACTED", "source_file": "src/HuntAndPeck/App.xaml.cs", "source_location": "L64", "weight": 1.0, "context": "parameter_type"}], "raw_calls": [{"caller_nid": "huntandpeck_app_xaml_app_showoverlay", "callee": "Close", "is_member_call": true, "source_file": "D:\\Workspace\\Vim_with_mouse\\src\\HuntAndPeck\\App.xaml.cs", "source_location": "L41", "receiver": null}, {"caller_nid": "huntandpeck_app_xaml_app_showoverlay", "callee": "Invoke", "is_member_call": true, "source_file": "D:\\Workspace\\Vim_with_mouse\\src\\HuntAndPeck\\App.xaml.cs", "source_location": "L42", "receiver": null}, {"caller_nid": "huntandpeck_app_xaml_app_showoverlay", "callee": "Show", "is_member_call": true, "source_file": "D:\\Workspace\\Vim_with_mouse\\src\\HuntAndPeck\\App.xaml.cs", "source_location": "L43", "receiver": null}, {"caller_nid": "huntandpeck_app_xaml_app_showdebugoverlay", "callee": "ShowDialog", "is_member_call": true, "source_file": "D:\\Workspace\\Vim_with_mouse\\src\\HuntAndPeck\\App.xaml.cs", "source_location": "L52", "receiver": null}, {"caller_nid": "huntandpeck_app_xaml_app_showoptions", "callee": "ShowDialog", "is_member_call": true, "source_file": "D:\\Workspace\\Vim_with_mouse\\src\\HuntAndPeck\\App.xaml.cs", "source_location": "L61", "receiver": null}, {"caller_nid": "huntandpeck_app_xaml_app_onstartup", "callee": "Contains", "is_member_call": true, "source_file": "D:\\Workspace\\Vim_with_mouse\\src\\HuntAndPeck\\App.xaml.cs", "source_location": "L66", "receiver": null}, {"caller_nid": "huntandpeck_app_xaml_app_onstartup", "callee": "GetForegroundWindow", "is_member_call": true, "source_file": "D:\\Workspace\\Vim_with_mouse\\src\\HuntAndPeck\\App.xaml.cs", "source_location": "L69", "receiver": null}, {"caller_nid": "huntandpeck_app_xaml_app_onstartup", "callee": "GetWindowRect", "is_member_call": true, "source_file": "D:\\Workspace\\Vim_with_mouse\\src\\HuntAndPeck\\App.xaml.cs", "source_location": "L73", "receiver": null}, {"caller_nid": "huntandpeck_app_xaml_app_onstartup", "callee": "Show", "is_member_call": true, "source_file": "D:\\Workspace\\Vim_with_mouse\\src\\HuntAndPeck\\App.xaml.cs", "source_location": "L76", "receiver": null}, {"caller_nid": "huntandpeck_app_xaml_app_onstartup", "callee": "EnumHintsAsync", "is_member_call": true, "source_file": "D:\\Workspace\\Vim_with_mouse\\src\\HuntAndPeck\\App.xaml.cs", "source_location": "L78", "receiver": null}, {"caller_nid": "huntandpeck_app_xaml_app_onstartup", "callee": "InvokeAsync", "is_member_call": true, "source_file": "D:\\Workspace\\Vim_with_mouse\\src\\HuntAndPeck\\App.xaml.cs", "source_location": "L81", "receiver": null}, {"caller_nid": "huntandpeck_app_xaml_app_onstartup", "callee": "PopulateHints", "is_member_call": true, "source_file": "D:\\Workspace\\Vim_with_mouse\\src\\HuntAndPeck\\App.xaml.cs", "source_location": "L81", "receiver": null}, {"caller_nid": "huntandpeck_app_xaml_app_onstartup", "callee": "Contains", "is_member_call": true, "source_file": "D:\\Workspace\\Vim_with_mouse\\src\\HuntAndPeck\\App.xaml.cs", "source_location": "L85", "receiver": null}, {"caller_nid": "huntandpeck_app_xaml_app_onstartup", "callee": "FindWindow", "is_member_call": true, "source_file": "D:\\Workspace\\Vim_with_mouse\\src\\HuntAndPeck\\App.xaml.cs", "source_location": "L88", "receiver": null}, {"caller_nid": "huntandpeck_app_xaml_app_onstartup", "callee": "GetWindowRect", "is_member_call": true, "source_file": "D:\\Workspace\\Vim_with_mouse\\src\\HuntAndPeck\\App.xaml.cs", "source_location": "L92", "receiver": null}, {"caller_nid": "huntandpeck_app_xaml_app_onstartup", "callee": "Show", "is_member_call": true, "source_file": "D:\\Workspace\\Vim_with_mouse\\src\\HuntAndPeck\\App.xaml.cs", "source_location": "L95", "receiver": null}, {"caller_nid": "huntandpeck_app_xaml_app_onstartup", "callee": "EnumHintsAsync", "is_member_call": true, "source_file": "D:\\Workspace\\Vim_with_mouse\\src\\HuntAndPeck\\App.xaml.cs", "source_location": "L97", "receiver": null}, {"caller_nid": "huntandpeck_app_xaml_app_onstartup", "callee": "InvokeAsync", "is_member_call": true, "source_file": "D:\\Workspace\\Vim_with_mouse\\src\\HuntAndPeck\\App.xaml.cs", "source_location": "L100", "receiver": null}, {"caller_nid": "huntandpeck_app_xaml_app_onstartup", "callee": "PopulateHints", "is_member_call": true, "source_file": "D:\\Workspace\\Vim_with_mouse\\src\\HuntAndPeck\\App.xaml.cs", "source_location": "L100", "receiver": null}, {"caller_nid": "huntandpeck_app_xaml_app_onstartup", "callee": "Shutdown", "is_member_call": true, "source_file": "D:\\Workspace\\Vim_with_mouse\\src\\HuntAndPeck\\App.xaml.cs", "source_location": "L109", "receiver": null}, {"caller_nid": "huntandpeck_app_xaml_app_onstartup", "callee": "Show", "is_member_call": true, "source_file": "D:\\Workspace\\Vim_with_mouse\\src\\HuntAndPeck\\App.xaml.cs", "source_location": "L129", "receiver": null}]}